swift_deps_map/__init__.py
swift_deps_map/__main__.py
swift_deps_map/cyto_viewer.html
swift_deps_map-0.1.0.dist-info/licenses/LICENSE
swift_deps_map-0.1.0.dist-info/METADATA
swift_deps_map-0.1.0.dist-info/WHEEL
swift_deps_map-0.1.0.dist-info/entry_points.txt
swift_deps_map-0.1.0.dist-info/top_level.txt
swift_deps_map-0.1.0.dist-info/RECORD
