Metadata-Version: 2.4
Name: swift-deps-map
Version: 0.1.0
Summary: Lightweight Swift file-level dependency mapper
Author: kidney
License-Expression: Apache-2.0
Requires-Python: >=3.9
License-File: LICENSE
Dynamic: license-file
